MANIFEST.in
README.rst
setup.py
test_pson.py
pson/__init__.py
pson/pson.py
pson.egg-info/PKG-INFO
pson.egg-info/SOURCES.txt
pson.egg-info/dependency_links.txt
pson.egg-info/requires.txt
pson.egg-info/top_level.txt
testdata/ar00498-98342.json